captif_slp/__init__.py
captif_slp/process.py
captif_slp/signal.py
captif_slp/slp.py
captif_slp/structures.py
captif_slp-0.21.dist-info/LICENSE
captif_slp-0.21.dist-info/METADATA
captif_slp-0.21.dist-info/WHEEL
captif_slp-0.21.dist-info/RECORD
