Metadata-Version: 2.3
Name: captif-slp
Version: 0.21
Summary: 
License: MIT
Keywords: CAPTIF
Author: John Bull
Requires-Python: >=3.9,<4.0
Classifier: License :: OSI Approved :: MIT License
Classifier: Programming Language :: Python :: 3
Classifier: Programming Language :: Python :: 3.9
Classifier: Programming Language :: Python :: 3.10
Classifier: Programming Language :: Python :: 3.11
Classifier: Programming Language :: Python :: 3.12
Classifier: Programming Language :: Python :: 3.13
Requires-Dist: click (>=8.1.7,<9.0.0)
Requires-Dist: matplotlib (>=3.4.3,<4.0.0)
Requires-Dist: pandas (>=2.1,<2.2)
Requires-Dist: psutil (>=5.8.0,<6.0.0)
Requires-Dist: pydantic (>=2,<3)
Requires-Dist: pyrsona (>=1.1,<2.0)
Requires-Dist: scipy (>=1.7.1,<2.0.0)
Project-URL: Homepage, https://github.com/captif-nz/captif-slp
